{
  "name": "application",
  "plural": "applications",
  "base": "PersistedModel",
  "idInjection": false,
  "options": {
    "validateUpsert": true
  },
  "properties": {
    "id": {
      "type": "string",
      "id": true,
      "required": true
    },
    "name": {
      "type": "string",
      "required": true
    },
    "serverKey": {
      "type": "string",
      "required": true
    },
    "description": {
      "type": "string"
    },
    "isDeleted": {
      "type": "boolean",
      "required": true,
      "default": false
    },
    "createdDate": {
      "type": "date"
    },
    "modifiedDate": {
      "type": "date"
    }
  },
  "validations": [],
  "relations": {},
  "acls": [],
  "methods": {}
}
